source_klaviyo/__init__.py
source_klaviyo/components/archived_to_per_partition_state_migration.py
source_klaviyo/components/campaign_details_transformations.py
source_klaviyo/components/included_fields_extractor.py
source_klaviyo/components/klaviyo_error_handler.py
source_klaviyo/components/per_partition_state_migration.py
source_klaviyo/manifest.yaml
source_klaviyo/run.py
source_klaviyo/schemas/campaigns.json
source_klaviyo/schemas/campaigns_detailed.json
source_klaviyo/schemas/flows.json
source_klaviyo/schemas/shared/campaign_properties.json
source_klaviyo/source.py
airbyte_source_klaviyo-2.13.1.dist-info/METADATA
airbyte_source_klaviyo-2.13.1.dist-info/WHEEL
airbyte_source_klaviyo-2.13.1.dist-info/entry_points.txt
airbyte_source_klaviyo-2.13.1.dist-info/RECORD
